COPYING
MANIFEST.in
README.rst
setup.py
tasks.py
etgen/__init__.py
etgen/etree.py
etgen/etree1.py
etgen/html.py
etgen/html2rst.py
etgen/setup_info.py
etgen/ui5xml.py
etgen/utils.py
etgen.egg-info/PKG-INFO
etgen.egg-info/SOURCES.txt
etgen.egg-info/dependency_links.txt
etgen.egg-info/requires.txt
etgen.egg-info/top_level.txt
etgen/intervat/__init__.py
etgen/intervat/validate.py
etgen/intervat/XSD/IntervatInputCommon_v0_7.xsd
etgen/intervat/XSD/IntervatIsoTypes_v0_7.xsd
etgen/intervat/XSD/NewAccuse_v0_7.xsd
etgen/intervat/XSD/NewICO-in_v0_7.xsd
etgen/intervat/XSD/NewLK-in_v0_7.xsd
etgen/intervat/XSD/NewMTN-in_v0_7.xsd
etgen/intervat/XSD/NewProRataAdjustment-in_v0_7.xsd
etgen/intervat/XSD/NewTVA-in_v0_7.xsd
etgen/intervat/XSD/NewVatRefund-in_v0_7.xsd
etgen/intervat/XSD/RtnList-1.3.xsd
etgen/intervat/XSD/VAT629-in_v0_7.xsd
etgen/intervat/XSD/adjreasons_v1.xsd
etgen/intervat/XSD/commontypes_v1.xsd
etgen/intervat/XSD/decreasons_v1.xsd
etgen/intervat/XSD/fiscalismessage_v1.xsd
etgen/intervat/XSD/goodsdescriptiontypes_v1.xsd
etgen/intervat/XSD/isotypes_v1.xsd
etgen/odf/__init__.py
etgen/sepa/__init__.py
etgen/sepa/xsdspy.py
tests/__init__.py
tests/test_docs.py
tests/test_utils.py